pynetdicom2/__init__.py
pynetdicom2/__version__.py
pynetdicom2/applicationentity.py
pynetdicom2/asceprovider.py
pynetdicom2/dimsemessages.py
pynetdicom2/dsutils.py
pynetdicom2/dulprovider.py
pynetdicom2/exceptions.py
pynetdicom2/fsm.py
pynetdicom2/pdu.py
pynetdicom2/sopclass.py
pynetdicom2/statuses.py
pynetdicom2/uids.py
pynetdicom2/userdataitems.py
pynetdicom2-0.9.7.dist-info/WHEEL
pynetdicom2-0.9.7.dist-info/METADATA
pynetdicom2-0.9.7.dist-info/RECORD
