Metadata-Version: 2.1
Name: pynetdicom2
Version: 0.9.7
Summary: pynetdicom2 is a pure python package implementing the DICOM network protocol
Home-page: https://github.com/blanebf/pynetdicom2
License: MIT
Keywords: medical,dicom,network
Author: Pavel 'Blane' Tuchin
Author-email: blane.public@gmail.com
Requires-Python: >=2.7, !=3.0.*, !=3.1.*, !=3.2.*, !=3.3.*, !=3.4.*
Classifier: Development Status :: 4 - Beta
Classifier: Intended Audience :: Developers
Classifier: Intended Audience :: Healthcare Industry
Classifier: Intended Audience :: Science/Research
Classifier: License :: OSI Approved :: MIT License
Classifier: Operating System :: OS Independent
Classifier: Programming Language :: Python
Classifier: Programming Language :: Python :: 2
Classifier: Programming Language :: Python :: 2.7
Classifier: Programming Language :: Python :: 3
Classifier: Programming Language :: Python :: 3.5
Classifier: Programming Language :: Python :: 3.6
Classifier: Programming Language :: Python :: 3.7
Classifier: Programming Language :: Python :: 3.8
Classifier: Programming Language :: Python :: 3.9
Classifier: Topic :: Software Development :: Libraries
Requires-Dist: pydicom (<=1.9); python_version >= "2.7" and python_version < "3.0"
Requires-Dist: pydicom (>=2.0,<3.0); python_version >= "3.4" and python_version < "4.0"
Requires-Dist: six
Requires-Dist: typing (==3.10.0.0); python_version >= "2.7" and python_version < "3.0"
Project-URL: Documentation, https://pynetdicom2.readthedocs.io/en/latest/
Project-URL: Repository, https://github.com/blanebf/pynetdicom2
